bpcs/__init__.py
bpcs/act_on_image.py
bpcs/array_bit_plane.py
bpcs/array_grid.py
bpcs/array_grid_old.py
bpcs/array_message.py
bpcs/batch_caller.py
bpcs/bpcs.py
bpcs/bpcs_steg.py
bpcs/bpcs_steg_capacity.py
bpcs/bpcs_steg_decode.py
bpcs/bpcs_steg_encode.py
bpcs/bpcs_steg_test.py
bpcs/images2gif.py
bpcs/logger.py
bpcs/make_gif.py
bpcs/plot_image.py
bpcs/test_utils.py
bpcs/text_to_image.py
bpcs-0.0.2.dist-info/DESCRIPTION.rst
bpcs-0.0.2.dist-info/METADATA
bpcs-0.0.2.dist-info/RECORD
bpcs-0.0.2.dist-info/WHEEL
bpcs-0.0.2.dist-info/metadata.json
bpcs-0.0.2.dist-info/pbr.json
bpcs-0.0.2.dist-info/top_level.txt
