Metadata-Version: 2.0
Name: bpcs
Version: 0.0.2
Summary: BPCS Steganography: embedding a message in a vessel image file
Home-page: UNKNOWN
Author: Jay Hennig
Author-email: mobeets@gmail.com
License: MIT
Keywords: bpcs steganography image bitplane complexity segmentation
Platform: UNKNOWN
